aminoac/__init__.py
aminoac/amns.mp3
aminoac-0.2.1.dist-info/METADATA
aminoac-0.2.1.dist-info/WHEEL
aminoac-0.2.1.dist-info/top_level.txt
aminoac-0.2.1.dist-info/RECORD
